examples/router_chat.py
routellm/__init__.py
routellm/calibrate_threshold.py
routellm/controller.py
routellm/openai_server.py
routellm/evals/benchmarks (Isaac Ong's conflicted copy 2024-07-05).py
routellm/evals/benchmarks.py
routellm/evals/evaluate.py
routellm/evals/find_contaminated.py
routellm/evals/gsm8k/generate_responses.py
routellm/evals/mmlu/domains.py
routellm/evals/mmlu/generate_responses.py
routellm/routers/routers.py
routellm/routers/causal_llm/configs.py
routellm/routers/causal_llm/llm_utils.py
routellm/routers/causal_llm/model.py
routellm/routers/causal_llm/prompt_format.py
routellm/routers/matrix_factorization/model.py
routellm/routers/matrix_factorization/train_matrix_factorization.py
routellm/routers/similarity_weighted/generate_embeddings.py
routellm/routers/similarity_weighted/utils.py
routellm/tests/test_openai_client.py
routellm/tests/test_openai_server.py
routellm-0.2.0.dist-info/LICENSE
routellm-0.2.0.dist-info/METADATA
routellm-0.2.0.dist-info/WHEEL
routellm-0.2.0.dist-info/top_level.txt
routellm-0.2.0.dist-info/RECORD
