Metadata-Version: 2.1
Name: routellm
Version: 0.2.0
Summary: A framework for serving and evaluating large language model routers.
Project-URL: Homepage, https://github.com/lm-sys/RouteLLM
Project-URL: Bug Tracker, https://github.com/lm-sys/RouteLLM/issues
Classifier: Programming Language :: Python :: 3
License-File: LICENSE
Requires-Dist: importlib-metadata; python_version < "3.10"
Requires-Dist: pyyaml
Requires-Dist: pydantic
Requires-Dist: numpy
Requires-Dist: pandas
Requires-Dist: torch
Requires-Dist: scikit-learn
Requires-Dist: tqdm
Requires-Dist: openai
Requires-Dist: transformers
Requires-Dist: datasets
Requires-Dist: litellm
Provides-Extra: serve
Requires-Dist: fastapi; extra == "serve"
Requires-Dist: shortuuid; extra == "serve"
Requires-Dist: uvicorn; extra == "serve"
Provides-Extra: eval
Requires-Dist: matplotlib; extra == "eval"
Requires-Dist: pandarallel; extra == "eval"
Requires-Dist: sglang; extra == "eval"
Requires-Dist: tiktoken; extra == "eval"
Provides-Extra: dev
Requires-Dist: black; extra == "dev"
Requires-Dist: isort; extra == "dev"
Requires-Dist: pre-commit; extra == "dev"
